[
  {
    "id": 1,
    "foto": "./foto.png",
    "descricao": "Lorem ipsum dolor sit amet, consectetur adipiscing elit.."
  },
  {
    "id": 2,
    "foto": "./foto.png",
    "descricao": "Lorem ipsum dolor sit amet, consectetur adipiscing elit"
  },
  {
    "id": 3,
    "foto": "./foto.png",
    "descricao": "Lorem ipsum dolor sit amet, consectetur adipiscing elit"
  },
  {
    "id": 4,
    "foto": "caminho/para/foto4.jpg",
    "descricao": "Lorem ipsum dolor sit amet, consectetur adipiscing elit"
  },{
    "id": 5,
    "foto": "./foto.png",
    "descricao": "Lorem ipsum dolor sit amet, consectetur adipiscing elit.."
  },
  {
    "id": 6,
    "foto": "./foto.png",
    "descricao": "Lorem ipsum dolor sit amet, consectetur adipiscing elit"
  },
  {
    "id": 7,
    "foto": "./foto.png",
    "descricao": "Lorem ipsum dolor sit amet, consectetur adipiscing elit"
  },
  {
    "id": 8,
    "foto": "caminho/para/foto4.jpg",
    "descricao": "Lorem ipsum dolor sit amet, consectetur adipiscing elit"
  },{
    "id": 9,
    "foto": "./foto.png",
    "descricao": "Lorem ipsum dolor sit amet, consectetur adipiscing elit.."
  },
  {
    "id": 10,
    "foto": "./foto.png",
    "descricao": "Lorem ipsum dolor sit amet, consectetur adipiscing elit"
  },
  {
    "id": 11,
    "foto": "./foto.png",
    "descricao": "Lorem ipsum dolor sit amet, consectetur adipiscing elit"
  },
  {
    "id": 12,
    "foto": "caminho/para/foto4.jpg",
    "descricao": "Lorem ipsum dolor sit amet, consectetur adipiscing elit"
  },{
    "id": 13,
    "foto": "./foto.png",
    "descricao": "Lorem ipsum dolor sit amet, consectetur adipiscing elit.."
  },
  {
    "id": 14,
    "foto": "./foto.png",
    "descricao": "Lorem ipsum dolor sit amet, consectetur adipiscing elit"
  },
  {
    "id": 15,
    "foto": "./foto.png",
    "descricao": "Lorem ipsum dolor sit amet, consectetur adipiscing elit"
  },
  {
    "id": 16,
    "foto": "caminho/para/foto4.jpg",
    "descricao": "Lorem ipsum dolor sit amet, consectetur adipiscing elit"
  }
]